walterscoapp/__init__.py
walterscoapp/app.py
walterscoapp/walterscoapp/__init__.py
walterscoapp-0.0.2.dist-info/LICENSE
walterscoapp-0.0.2.dist-info/METADATA
walterscoapp-0.0.2.dist-info/WHEEL
walterscoapp-0.0.2.dist-info/top_level.txt
walterscoapp-0.0.2.dist-info/RECORD
